[
    {
        "name": "storefront",
        "full_name": "moonpay/storefront",
        "url": "https://github.com/moonpay/storefront",
        "stars": 4,
        "updated_at": "2025-03-06T13:56:01Z",
        "description": null,
        "size_kb": 15643,
        "languages": {
            "TypeScript": 70510,
            "SCSS": 18339,
            "HTML": 1594,
            "JavaScript": 874
        }
    },
    {
        "name": "mobile-sdk-ios",
        "full_name": "moonpay/mobile-sdk-ios",
        "url": "https://github.com/moonpay/mobile-sdk-ios",
        "stars": 14,
        "updated_at": "2025-02-17T23:31:08Z",
        "description": null,
        "size_kb": 120195,
        "languages": {
            "Objective-C": 402640,
            "Swift": 398
        }
    },
    {
        "name": "devops-challenge",
        "full_name": "moonpay/devops-challenge",
        "url": "https://github.com/moonpay/devops-challenge",
        "stars": 1,
        "updated_at": "2024-01-11T07:08:42Z",
        "description": "DevOps Challenge Application",
        "size_kb": 803,
        "languages": {
            "TypeScript": 11016,
            "JavaScript": 539,
            "CSS": 407
        }
    },
    {
        "name": "react-native-bottom-sheet",
        "full_name": "moonpay/react-native-bottom-sheet",
        "url": "https://github.com/moonpay/react-native-bottom-sheet",
        "stars": 0,
        "updated_at": "2024-10-09T16:35:56Z",
        "description": "A performant interactive bottom sheet with fully configurable options \ud83d\ude80",
        "size_kb": 10914,
        "languages": {
            "TypeScript": 302814,
            "Java": 15440,
            "JavaScript": 9004,
            "Handlebars": 7591,
            "C++": 6948,
            "Objective-C++": 4452,
            "Makefile": 1510,
            "Ruby": 985,
            "Objective-C": 396
        }
    },
    {
        "name": "moonpay-sign",
        "full_name": "moonpay/moonpay-sign",
        "url": "https://github.com/moonpay/moonpay-sign",
        "stars": 0,
        "updated_at": "2025-02-07T12:01:25Z",
        "description": "Backend endpoint for signature generation",
        "size_kb": 92,
        "languages": {
            "TypeScript": 6181,
            "JavaScript": 528,
            "CSS": 345
        }
    }
]
